microservice_story_manager/__init__.py
microservice_story_manager/error_messages.py
microservice_story_manager/fitness_functions.py
microservice_story_manager/genetic_microservice_assigner.py
microservice_story_manager/genetic_microservice_assigner_old.py
microservice_story_manager/metrics_visualizer.py
microservice_story_manager/microservice_manager.py
microservice_story_manager/microservice_metrics.py
microservice_story_manager/microservice_visualizer.py
microservice_story_manager/quick_start.ipynb
microservice_story_manager/quick_start.py
microservice_story_manager/semantic_similarity.py
microservice_story_manager/simple_test.py
microservice_story_manager/user_story_manager.py
microservice_story_manager-0.2.0.dist-info/METADATA
microservice_story_manager-0.2.0.dist-info/WHEEL
microservice_story_manager-0.2.0.dist-info/RECORD
