Metadata-Version: 2.1
Name: microservice-story-manager
Version: 0.2.0
Summary: Microservice Story Manager is a Python library for optimizing user story assignments in microservice architectures. It features story and microservice management, genetic algorithm optimization, and visualization tools. The library calculates metrics like coupling and cohesion, allows comparison of optimization strategies, and supports CSV data loading. It aids in microservice design decisions, helping maximize cohesion and minimize coupling in software architectures.
Author: radix1001
Author-email: luis@thedogcompany.cl
Requires-Python: >=3.11,<4.0
Classifier: Programming Language :: Python :: 3
Classifier: Programming Language :: Python :: 3.11
Requires-Dist: deap (>=1.4.1,<2.0.0)
Requires-Dist: jupyter (>=1.0.0,<2.0.0)
Requires-Dist: matplotlib (>=3.9.1,<4.0.0)
Requires-Dist: mpld3 (>=0.5.10,<0.6.0)
Requires-Dist: networkx (>=3.3,<4.0)
Requires-Dist: spacy (>=3.7.5,<4.0.0)
